mmusicc/__init__.py
mmusicc/__main__.py
mmusicc/_init.py
mmusicc/metadata.py
mmusicc/mmusicc.py
mmusicc/version.py
mmusicc/data/config.yaml
mmusicc/database/__init__.py
mmusicc/database/metadb.py
mmusicc/formats/__init__.py
mmusicc/formats/_audio.py
mmusicc/formats/_misc.py
mmusicc/formats/_util.py
mmusicc/formats/mp3.py
mmusicc/formats/xiph.py
mmusicc/util/__init__.py
mmusicc/util/allocationmap.py
mmusicc/util/ffmpeg.py
mmusicc/util/importhelper.py
mmusicc/util/logger.py
mmusicc/util/metadatadict.py
mmusicc/util/misc.py
mmusicc/util/path.py
mmusicc/util/util.py
test/__init__.py
test/_util.py
test/conftest.py
test/test_database.py
test/test_formats.py
test/test_metadata.py
test/test_mmusicc.py
test/test_util.py
mmusicc-0.3.0a2.dist-info/LICENSE
mmusicc-0.3.0a2.dist-info/METADATA
mmusicc-0.3.0a2.dist-info/WHEEL
mmusicc-0.3.0a2.dist-info/entry_points.txt
mmusicc-0.3.0a2.dist-info/top_level.txt
mmusicc-0.3.0a2.dist-info/RECORD
