Metadata-Version: 2.1
Name: mmusicc
Version: 0.3.0a2
Summary: A lightweight audio file and metadata control and synchronization program to transfer the changes made in a master music library to a derived music library.
Home-page: https://github.com/jonolt/mmusicc
Author: Johannes Nolte
Author-email: jonolt@mailbox.org
License: UNKNOWN
Project-URL: Documentation, https://github.com/jonolt/mmusicc
Platform: UNKNOWN
Classifier: Development Status :: 4 - Beta
Classifier: Programming Language :: Python
Classifier: Programming Language :: Python :: 3.6
Classifier: Programming Language :: Python :: 3.7
Classifier: Programming Language :: Python :: 3.8
Classifier: License :: OSI Approved :: GNU General Public License v3 or later (GPLv3+)
Classifier: Operating System :: POSIX
Classifier: Topic :: Multimedia :: Sound/Audio
Classifier: Topic :: Multimedia :: Sound/Audio :: Conversion
Classifier: Topic :: Multimedia :: Sound/Audio :: Editors
Classifier: Environment :: Console
Classifier: Intended Audience :: End Users/Desktop
Requires-Python: >=3.6
Requires-Dist: mutagen (>=1.41.0)
Requires-Dist: PyYAML (>=3.01)
Requires-Dist: SQLAlchemy (>=1.3.0)
